django_easy_instagram/__init__.py
django_easy_instagram/scraper.py
django_easy_instagram/settings.py
django_easy_instagram/templatetags/__init__.py
django_easy_instagram/templatetags/instagram_client.py
django_easy_instagram-1.0.3.dist-info/LICENSE
django_easy_instagram-1.0.3.dist-info/METADATA
django_easy_instagram-1.0.3.dist-info/WHEEL
django_easy_instagram-1.0.3.dist-info/top_level.txt
django_easy_instagram-1.0.3.dist-info/RECORD
