Metadata-Version: 2.2
Name: django-easy-instagram
Version: 1.0.3
Summary: Instagram client for Django.
Home-page: https://github.com/TomAnthony/django-easy-instagram/
Author: Tom Anthony
Author-email: django@tomanthony.co.uk
License: BSD-3 License
Platform: any
License-File: LICENSE
Requires-Dist: requests
Requires-Dist: sorl-thumbnail
Dynamic: author
Dynamic: author-email
Dynamic: description
Dynamic: description-content-type
Dynamic: home-page
Dynamic: license
Dynamic: platform
Dynamic: requires-dist
Dynamic: summary
